dali_renderer/__about__.py
dali_renderer/__init__.py
dali_renderer/config.py
dali_renderer/dali.py
dali_renderer/py.typed
dali_renderer/assets/background_wrapper.svg
dali_renderer/assets/fonts/Fira/Fira.ttf
dali_renderer/assets/fonts/Hack/Hack.ttf
dali_renderer/assets/fonts/Inconsolata/Inconsolata.ttf
dali_renderer/assets/fonts/JetBrains/JetBrains.ttf
dali_renderer/renders/DaliFontManager.py
dali_renderer/renders/DaliImageFormatter.py
dali_renderer/renders/__init__.py
dali_renderer/renders/svg.py
dali_renderer-1.0.0b2.dist-info/METADATA
dali_renderer-1.0.0b2.dist-info/WHEEL
dali_renderer-1.0.0b2.dist-info/licenses/LICENSE
dali_renderer-1.0.0b2.dist-info/RECORD
