Metadata-Version: 2.1
Name: dali_renderer
Version: 1.0.0b2
Summary: Powerful rendering of your source code.
Project-URL: Documentation, https://github.com/foozzi/dali#readme
Project-URL: Issues, https://github.com/foozzi/dali/issues
Project-URL: Source, https://github.com/foozzi/dali
Author-email: fz0x1 <me@fz0x1.wtf>
License-Expression: BSD-3-Clause
License-File: LICENSE
Classifier: Development Status :: 4 - Beta
Classifier: Programming Language :: Python
Classifier: Programming Language :: Python :: 3.7
Classifier: Programming Language :: Python :: 3.8
Classifier: Programming Language :: Python :: 3.9
Classifier: Programming Language :: Python :: 3.10
Classifier: Programming Language :: Python :: 3.11
Classifier: Programming Language :: Python :: Implementation :: CPython
Classifier: Programming Language :: Python :: Implementation :: PyPy
Requires-Python: >=3.7
Requires-Dist: beautifulsoup4~=4.11.1
Requires-Dist: cairocffi~=1.4.0
Requires-Dist: cairosvg~=2.5.2
Requires-Dist: cffi~=1.15.1
Requires-Dist: cssselect2~=0.7.0
Requires-Dist: defusedxml~=0.7.1
Requires-Dist: lxml~=4.9.2
Requires-Dist: pycparser~=2.21
Requires-Dist: pygments~=2.14.0
Requires-Dist: soupsieve~=2.3.2.post1
Requires-Dist: tinycss2~=1.2.1
Requires-Dist: webencodings~=0.5.1
Requires-Dist: xcffib~=1.2.0
